{
  "providerName": "ebay.com",
  "openApiRaw": "https://developer.ebay.com/api-docs/master/sell/compliance/openapi/3/sell_compliance_v1_oas3.json",
  "homepage": "ebay.com",
  "serviceName": "sell-compliance",
  "apiVersion": "1.4.1",
  "apiBaseUrl": "https://api.ebay.com{basePath}",
  "apiDescription": "Service for providing information to sellers about their listings being non-compliant, or at risk for becoming non-compliant, against eBay listing policies.",
  "apiTitle": "Compliance API",
  "endpoints": 3,
  "sdkMethods": 3,
  "schemas": 13,
  "parameters": 10,
  "difficultyScore": 12,
  "difficulty": "Easy"
}