{
  "openapiDirectoryPath": "tcgdex.net/2.0.0/openapi.yaml",
  "providerName": "tcgdex.net",
  "openApiRaw": "https://api.tcgdex.net/v2/openapi.yaml",
  "securitySchemes": {},
  "homepage": "tcgdex.net",
  "apiVersion": "2.0.0",
  "apiBaseUrl": "https://api.tcgdex.net/v2/{lang}",
  "apiDescription": "A Multilanguage Pokémon TCG Database with Cards Pictures and most of the informations contained on the cards.\nYou can find out more about TCGdex at [https://www.tcgdex.net](https://www.tcgdex.net) or on [Discord](https://discord.gg/NehYTAhsZE).",
  "apiTitle": "TCGdex API",
  "endpoints": 33,
  "sdkMethods": 33,
  "schemas": 8,
  "parameters": 18,
  "contactUrl": "https://github.com/tcgdex/cards-database",
  "contactEmail": "contact@tcgdex.net",
  "difficultyScore": 41.5,
  "difficulty": "Easy"
}