[
  {
    "parentCategory": "Artificial Intelligence",
    "subCategories": [
      {
        "category": "AI Tools",
        "page": "ai-tools",
        "subpath": "/sdk/category/ai-tools"
      },
      {
        "category": "Text-to-Speech",
        "page": "text-to-speech",
        "subpath": "/sdk/category/text-to-speech"
      },
      {
        "category": "Video Generation",
        "page": "video-generation",
        "subpath": "/sdk/category/video-generation"
      },
      {
        "category": "Natural Language Processing",
        "page": "natural-language-processing",
        "subpath": "/sdk/category/natural-language-processing"
      }
    ],
    "page": "artificial-intelligence",
    "subpath": "/sdk/category/artificial-intelligence"
  },
  {
    "parentCategory": "Business Intelligence",
    "subCategories": [
      {
        "category": "Analytics",
        "page": "analytics",
        "subpath": "/sdk/category/analytics"
      },
      {
        "category": "Reviews",
        "page": "reviews",
        "subpath": "/sdk/category/reviews"
      }
    ],
    "page": "business-intelligence",
    "subpath": "/sdk/category/business-intelligence"
  },
  {
    "parentCategory": "Commerce",
    "subCategories": [
      {
        "category": "Payment Processing",
        "page": "payment-processing",
        "subpath": "/sdk/category/payment-processing"
      },
      {
        "category": "Accounting",
        "page": "accounting",
        "subpath": "/sdk/category/accounting"
      },
      {
        "category": "eCommerce",
        "page": "e-commerce",
        "subpath": "/sdk/category/e-commerce"
      }
    ],
    "page": "commerce",
    "subpath": "/sdk/category/commerce"
  },
  {
    "parentCategory": "Communication",
    "subCategories": [
      {
        "category": "Community",
        "page": "community",
        "subpath": "/sdk/category/community"
      },
      {
        "category": "Team Collaboration",
        "page": "team-collaboration",
        "subpath": "/sdk/category/team-collaboration"
      },
      {
        "category": "Email",
        "page": "email",
        "subpath": "/sdk/category/email"
      },
      {
        "category": "Team Chat",
        "page": "team-chat",
        "subpath": "/sdk/category/team-chat"
      },
      {
        "category": "Video Conferencing",
        "page": "video-conferencing",
        "subpath": "/sdk/category/video-conferencing"
      },
      {
        "category": "Phone & SMS",
        "page": "phone-sms",
        "subpath": "/sdk/category/phone-sms"
      }
    ],
    "page": "communication",
    "subpath": "/sdk/category/communication"
  },
  {
    "parentCategory": "Content & Files",
    "subCategories": [
      {
        "category": "Images & Design",
        "page": "images-design",
        "subpath": "/sdk/category/images-design"
      },
      {
        "category": "Video & Audio",
        "page": "video-audio",
        "subpath": "/sdk/category/video-audio"
      },
      {
        "category": "File Management & Storage",
        "page": "file-management-storage",
        "subpath": "/sdk/category/file-management-storage"
      },
      {
        "category": "Documents",
        "page": "documents",
        "subpath": "/sdk/category/documents"
      }
    ],
    "page": "content-files",
    "subpath": "/sdk/category/content-files"
  },
  {
    "parentCategory": "Data",
    "subCategories": [
      {
        "category": "Science",
        "page": "science",
        "subpath": "/sdk/category/science"
      },
      {
        "category": "Knowledge",
        "page": "knowledge",
        "subpath": "/sdk/category/knowledge"
      }
    ],
    "page": "data",
    "subpath": "/sdk/category/data"
  },
  {
    "parentCategory": "Human Resources",
    "subCategories": [
      {
        "category": "HR Talent & Recruitment",
        "page": "hr-talent-recruitment",
        "subpath": "/sdk/category/hr-talent-recruitment"
      }
    ],
    "page": "human-resources",
    "subpath": "/sdk/category/human-resources"
  },
  {
    "parentCategory": "Internet of Things",
    "subCategories": [
      {
        "category": "Printing",
        "page": "printing",
        "subpath": "/sdk/category/printing"
      }
    ],
    "page": "internet-of-things",
    "subpath": "/sdk/category/internet-of-things"
  },
  {
    "parentCategory": "IT Operations",
    "subCategories": [
      {
        "category": "Developer Tools",
        "page": "developer-tools",
        "subpath": "/sdk/category/developer-tools"
      },
      {
        "category": "Security & Identity Tools",
        "page": "security-identity-tools",
        "subpath": "/sdk/category/security-identity-tools"
      },
      {
        "category": "Databases",
        "page": "databases",
        "subpath": "/sdk/category/databases"
      }
    ],
    "page": "it-operations",
    "subpath": "/sdk/category/it-operations"
  },
  {
    "parentCategory": "Lifestyle & Entertainment",
    "subCategories": [
      {
        "category": "News & Lifestyle",
        "page": "news-lifestyle",
        "subpath": "/sdk/category/news-lifestyle"
      },
      {
        "category": "Music",
        "page": "music",
        "subpath": "/sdk/category/music"
      }
    ],
    "page": "lifestyle-entertainment",
    "subpath": "/sdk/category/lifestyle-entertainment"
  },
  {
    "parentCategory": "Marketing",
    "subCategories": [
      {
        "category": "Marketing Automation",
        "page": "marketing-automation",
        "subpath": "/sdk/category/marketing-automation"
      },
      {
        "category": "Transactional Email",
        "page": "transactional-email",
        "subpath": "/sdk/category/transactional-email"
      },
      {
        "category": "Social Media Marketing",
        "page": "social-media-marketing",
        "subpath": "/sdk/category/social-media-marketing"
      }
    ],
    "page": "marketing",
    "subpath": "/sdk/category/marketing"
  },
  {
    "parentCategory": "Productivity",
    "subCategories": [
      {
        "category": "Project Management",
        "page": "project-management",
        "subpath": "/sdk/category/project-management"
      },
      {
        "category": "Product Management",
        "page": "product-management",
        "subpath": "/sdk/category/product-management"
      }
    ],
    "page": "productivity",
    "subpath": "/sdk/category/productivity"
  },
  {
    "parentCategory": "Sales & CRM",
    "subCategories": [
      {
        "category": "Signatures",
        "page": "signatures",
        "subpath": "/sdk/category/signatures"
      },
      {
        "category": "Forms & Surveys",
        "page": "forms-surveys",
        "subpath": "/sdk/category/forms-surveys"
      }
    ],
    "page": "sales-crm",
    "subpath": "/sdk/category/sales-crm"
  },
  {
    "parentCategory": "Website & App Building",
    "subCategories": [
      {
        "category": "Website Builders",
        "page": "website-builders",
        "subpath": "/sdk/category/website-builders"
      }
    ],
    "page": "website-app-building",
    "subpath": "/sdk/category/website-app-building"
  }
]